README.md
setup.cfg
setup.py
func_bk/__init__.py
func_bk/django.py
func_bk/fast_api.py
func_bk.egg-info/PKG-INFO
func_bk.egg-info/SOURCES.txt
func_bk.egg-info/dependency_links.txt
func_bk.egg-info/not-zip-safe
func_bk.egg-info/top_level.txt