Metadata-Version: 2.1
Name: func_bk
Version: 1.5.9
Summary: add function for normal python and add class(for inheritance) for django
Author-email: lilo.pio147@mail.ru
